b4tf/__init__.py
b4tf/utils.py
b4tf/models/__init__.py
b4tf/models/base.py
b4tf/models/mcbn.py
b4tf/models/pbp.py
b4tf-1.1.2.dist-info/LICENSE
b4tf-1.1.2.dist-info/METADATA
b4tf-1.1.2.dist-info/WHEEL
b4tf-1.1.2.dist-info/top_level.txt
b4tf-1.1.2.dist-info/RECORD
