Metadata-Version: 2.1
Name: b4tf
Version: 1.1.2
Summary: Bayian Neural Network for TensorFlow
Home-page: https://gitlab.com/ymd_h/b4tf
Author: Hiroyuki Yamada
License: UNKNOWN
Platform: UNKNOWN
Classifier: Development Status :: 4 - Beta
Classifier: Intended Audience :: Developers
Classifier: Intended Audience :: Science/Research
Classifier: License :: OSI Approved :: MIT License
Classifier: Programming Language :: Python :: 3 :: Only
Classifier: Topic :: Scientific/Engineering :: Artificial Intelligence
Requires-Dist: tensorflow (>=2)
Requires-Dist: tensorflow-probability
